pyxdu/__init__.py
pyxdu/__main__.py
pyxdu/tk.py
pyxdu/xdu.py
pyxdu-1.0.1.dist-info/entry_points.txt
pyxdu-1.0.1.dist-info/LICENSE.txt
pyxdu-1.0.1.dist-info/WHEEL
pyxdu-1.0.1.dist-info/METADATA
pyxdu-1.0.1.dist-info/RECORD
