Metadata-Version: 2.1
Name: pyxdu
Version: 1.0.1
Summary: Display the output of "du" in a window.
Home-page: https://github.com/vlasovskikh/pyxdu
License: MIT
Keywords: gui,disk-usage,tkinter,xdu,disk-space
Author: Andrey Vlasovskikh
Author-email: andrey.vlasovskikh@gmail.com
Requires-Python: >=3.8,<4.0
Classifier: Development Status :: 5 - Production/Stable
Classifier: Environment :: MacOS X
Classifier: Environment :: X11 Applications
Classifier: Intended Audience :: End Users/Desktop
Classifier: License :: OSI Approved :: MIT License
Classifier: Programming Language :: Python :: 3
Classifier: Programming Language :: Python :: 3.8
Classifier: Programming Language :: Python :: 3.9
Classifier: Programming Language :: Python :: 3.10
Classifier: Programming Language :: Python :: 3.11
Classifier: Topic :: Desktop Environment :: File Managers
Classifier: Topic :: System :: Filesystems
Requires-Dist: docopt (>=0.6.2,<0.7.0)
Project-URL: Repository, https://github.com/vlasovskikh/pyxdu
